sess_i/__init__.py
sess_i/base/__init__.py
sess_i/base/main.py
sess_i-0.2.1.dist-info/LICENSE
sess_i-0.2.1.dist-info/METADATA
sess_i-0.2.1.dist-info/WHEEL
sess_i-0.2.1.dist-info/RECORD
