Metadata-Version: 2.1
Name: sess-i
Version: 0.2.1
Summary: A helper package for handling multi-page apps built using Streamlit
Home-page: https://github.com/llegregam/streamlit_sess_i
License: GNU General Public License v3 or later (GPLv3+)
Author: llegregam
Author-email: legregam@insa-toulouse.fr
Requires-Python: >=3.8, !=2.7.*, !=3.0.*, !=3.1.*, !=3.2.*, !=3.3.*, !=3.4.*, !=3.5.*, !=3.6.*, !=3.7.*
Classifier: License :: Other/Proprietary License
Classifier: Programming Language :: Python :: 3
Classifier: Programming Language :: Python :: 3.9
Classifier: Programming Language :: Python :: 3.10
Classifier: Programming Language :: Python :: 3.11
Classifier: Programming Language :: Python :: 3.12
Classifier: Programming Language :: Python :: 3.13
Requires-Dist: streamlit (>=1.33.0,<2.0.0)
